e2b_fastmcp_server/__init__.py
e2b_fastmcp_server/__main__.py
e2b_fastmcp_server/server.py
e2b_fastmcp_server-0.2.2.dist-info/METADATA
e2b_fastmcp_server-0.2.2.dist-info/WHEEL
e2b_fastmcp_server-0.2.2.dist-info/entry_points.txt
e2b_fastmcp_server-0.2.2.dist-info/top_level.txt
e2b_fastmcp_server-0.2.2.dist-info/RECORD
