Metadata-Version: 2.4
Name: e2b-fastmcp-server
Version: 0.2.2
Summary: E2B sandbox-backed FastMCP server
Requires-Python: >=3.12
Requires-Dist: mcp[cli]>=1.15.0
Requires-Dist: fastmcp>=0.2.0
Requires-Dist: e2b-code-interpreter<2.0.0,>=1.0.2
Requires-Dist: python-dotenv>=1.0.1
Requires-Dist: build>=1.3.0
Requires-Dist: twine>=6.2.0
